hybrid_search/__init__.py
hybrid_search/novel_embeddings.py
hybrid_search/opensearch_hybrid_search.py
hybrid_search-0.0.15.dist-info/LICENSE
hybrid_search-0.0.15.dist-info/METADATA
hybrid_search-0.0.15.dist-info/WHEEL
hybrid_search-0.0.15.dist-info/top_level.txt
hybrid_search-0.0.15.dist-info/RECORD
