Metadata-Version: 2.1
Name: hybrid_search
Version: 0.0.15
Summary: Hybrid search with OpenSearch and Langchain
Author: Alex Karmazin
Author-email: <karmazinalex@gmail.com>
Keywords: python,llm,science,review,hybrid search,semantic search
Classifier: Development Status :: 2 - Pre-Alpha
Classifier: Intended Audience :: Developers
Classifier: Programming Language :: Python :: 3.10
Classifier: Programming Language :: Python :: 3.11
Classifier: Operating System :: Unix
Classifier: Operating System :: MacOS :: MacOS X
Classifier: Operating System :: Microsoft :: Windows
License-File: LICENSE
Requires-Dist: pycomfort >=0.0.15
Requires-Dist: click
Requires-Dist: transformers >=4.35.2
Requires-Dist: sentence-transformers
Requires-Dist: opensearch-py >=2.6.0
Requires-Dist: langchain >=0.2.11
Requires-Dist: langchain-community >=0.2.10
Requires-Dist: langchain-huggingface >=0.0.3
